{"liters_of_bottled_beer": {"organic red helles": 2000.0, "organic pilsner": 1500.0, "organic dunkel": 1350.0}, "equipment_state": {"albert": {"active": true, "stage": "Conditioning", "run_length": 1209600, "unix_time_started": 1577207372, "type": "organic red helles", "volume": 700, "gyle_number": 1019}, "brigadier": {"active": true, "stage": "Fermenting", "run_length": 4320000, "unix_time_started": 1575213573, "type": "organic red helles", "volume": 800, "gyle_number": 1001}, "camilla": {"active": true, "stage": "Conditioning", "run_length": 1209600, "unix_time_started": 1575473589, "type": "organic pilsner", "volume": 1000, "gyle_number": 1015}, "dylon": {"active": true, "stage": "Conditioning", "run_length": 1209600, "unix_time_started": 1575377656, "type": "organic red helles", "volume": 800, "gyle_number": 1014}, "emily": {"active": true, "stage": "Conditioning", "run_length": 1209600, "unix_time_started": 1576939869, "type": "organic red helles", "volume": 1000, "gyle_number": 1033}, "florence": {"active": false, "stage": "None", "run_length": 0, "unix_time_started": 0, "type": "None", "volume": 0, "gyle_number": 0}, "gertrude": {"active": false, "stage": "None", "run_length": 0, "unix_time_started": 0, "type": "None", "volume": 0, "gyle_number": 0}, "harry": {"active": false, "stage": "None", "run_length": 0, "unix_time_started": 0, "type": "None", "volume": 0, "gyle_number": 0}, "r2d2": {"active": false, "stage": "None", "run_length": 0, "unix_time_started": 0, "type": "None", "volume": 0, "gyle_number": 0}}, "current_gyle_number": 1034}